[
{"id": 292970, "rank": 1, "name": "Filament", "scraped_at": 1667628636.179819},
{"id": 214743, "rank": 2, "name": "Phoning Home", "scraped_at": 1667628636.179819},
{"id": 246397, "rank": 3, "name": "Rising Storm 2: Vietnam", "scraped_at": 1667628636.179819},
{"id": 208043, "rank": 4, "name": "Shadow Tactics: Blades of the Shogun", "scraped_at": 1667628636.179819},
{"id": 314959, "rank": 5, "name": "Alba: a Wildlife Adventure", "scraped_at": 1667628636.179819},
{"id": 313082, "rank": 6, "name": "Destroy All Humans! (2020)", "scraped_at": 1667628636.179819},
{"id": 374036, "rank": 7, "name": "Heavenly Bodies", "scraped_at": 1667628636.179819},
{"id": 156913, "rank": 8, "name": "DUELYST", "scraped_at": 1667628636.179819},
{"id": 75636, "rank": 9, "name": "Metroid Prime Trilogy", "scraped_at": 1667628636.179819},
{"id": 76420, "rank": 10, "name": "Combat", "scraped_at": 1667628636.179819},
{"id": 84628, "rank": 11, "name": "Fallout: New Vegas", "scraped_at": 1667628636.179819},
{"id": 140545, "rank": 12, "name": "Hearthstone: Heroes of Warcraft", "scraped_at": 1667628636.179819},
{"id": 194926, "rank": 13, "name": "Stardew Valley", "scraped_at": 1667628636.179819},
{"id": 202164, "rank": 14, "name": "God of War (2018)", "scraped_at": 1667628636.179819},
{"id": 230070, "rank": 15, "name": "Legendary DXP: A Fantasy Deck Building Game", "scraped_at": 1667628636.179819},
{"id": 247167, "rank": 16, "name": "Artifact", "scraped_at": 1667628636.179819},
{"id": 315149, "rank": 17, "name": "TREE", "scraped_at": 1667628636.179819},
{"id": 68433, "rank": 18, "name": "Prince of Persia: The Sands of Time", "scraped_at": 1667628636.179819},
{"id": 68799, "rank": 19, "name": "Dead Rising", "scraped_at": 1667628636.179819},
{"id": 69174, "rank": 20, "name": "Shenmue", "scraped_at": 1667628636.179819},
{"id": 70414, "rank": 21, "name": "Planescape: Torment", "scraped_at": 1667628636.179819},
{"id": 71181, "rank": 22, "name": "Another World", "scraped_at": 1667628636.179819},
{"id": 71423, "rank": 23, "name": "Duke Nukem 3D", "scraped_at": 1667628636.179819},
{"id": 71443, "rank": 24, "name": "Jazz Jackrabbit 2", "scraped_at": 1667628636.179819},
{"id": 71465, "rank": 25, "name": "Alan Wake", "scraped_at": 1667628636.179819},
{"id": 72052, "rank": 26, "name": "God of War (2005)", "scraped_at": 1667628636.179819},
{"id": 74049, "rank": 27, "name": "Star Wars: Battlefront (2004)", "scraped_at": 1667628636.179819},
{"id": 74562, "rank": 28, "name": "The Witcher", "scraped_at": 1667628636.179819},
{"id": 75710, "rank": 29, "name": "Super Street Fighter II", "scraped_at": 1667628636.179819},
{"id": 76720, "rank": 30, "name": "God of War: Chains of Olympus", "scraped_at": 1667628636.179819},
{"id": 77415, "rank": 31, "name": "Total Annihilation", "scraped_at": 1667628636.179819},
{"id": 77923, "rank": 32, "name": "Medieval II: Total War Gold Edition", "scraped_at": 1667628636.179819},
{"id": 90679, "rank": 33, "name": "Bang! the Official Video Game", "scraped_at": 1667628636.179819},
{"id": 102345, "rank": 34, "name": "Mass Effect 3", "scraped_at": 1667628636.179819},
{"id": 104984, "rank": 35, "name": "TearRing Saga", "scraped_at": 1667628636.179819},
{"id": 111765, "rank": 36, "name": "Elder Sign: Omens", "scraped_at": 1667628636.179819},
{"id": 118957, "rank": 37, "name": "Dominion by Donald X. Vaccarino", "scraped_at": 1667628636.179819},
{"id": 119150, "rank": 38, "name": "Titan HD", "scraped_at": 1667628636.179819},
{"id": 131814, "rank": 39, "name": "Fallout: New Vegas \u2013 Ultimate edition", "scraped_at": 1667628636.179819},
{"id": 142346, "rank": 40, "name": "Eclipse: New Dawn for the Galaxy", "scraped_at": 1667628636.179819},
{"id": 156044, "rank": 41, "name": "Batman: Arkham Knight", "scraped_at": 1667628636.179819},
{"id": 159228, "rank": 42, "name": "Armello", "scraped_at": 1667628636.179819},
{"id": 176855, "rank": 43, "name": "Coup", "scraped_at": 1667628636.179819},
{"id": 202167, "rank": 44, "name": "Resident Evil 7: Biohazard", "scraped_at": 1667628636.179819},
{"id": 203189, "rank": 45, "name": "Scorn", "scraped_at": 1667628636.179819},
{"id": 215050, "rank": 46, "name": "The Last of Us Part II", "scraped_at": 1667628636.179819},
{"id": 218508, "rank": 47, "name": "Mansions of Madness", "scraped_at": 1667628636.179819},
{"id": 238427, "rank": 48, "name": "Bohnanza The Duel", "scraped_at": 1667628636.179819},
{"id": 242969, "rank": 49, "name": "Into the Breach", "scraped_at": 1667628636.179819},
{"id": 257578, "rank": 50, "name": "Ganz Sch\u00f6n Clever", "scraped_at": 1667628636.179819}
]