[
{"id": 298694, "rank": 1, "name": "Them's Fightin' Herds", "scraped_at": 1671603025.498129},
{"id": 231335, "rank": 2, "name": "Frostpunk", "scraped_at": 1671603025.498129},
{"id": 142678, "rank": 3, "name": "Wolfenstein: The New Order", "scraped_at": 1671603025.498129},
{"id": 135602, "rank": 4, "name": "Broken Sword: Director's Cut", "scraped_at": 1671603025.498129},
{"id": 255017, "rank": 5, "name": "Sable", "scraped_at": 1671603025.498129},
{"id": 359387, "rank": 6, "name": "The USB Stick Found in the Grass", "scraped_at": 1671603025.498129},
{"id": 120241, "rank": 7, "name": "Dragon Age: Inquisition", "scraped_at": 1671603025.498129},
{"id": 202164, "rank": 8, "name": "God of War (2018)", "scraped_at": 1671603025.498129},
{"id": 247167, "rank": 9, "name": "Artifact", "scraped_at": 1671603025.498129},
{"id": 303262, "rank": 10, "name": "Monster Train", "scraped_at": 1671603025.498129},
{"id": 353407, "rank": 11, "name": "Regicide Companion", "scraped_at": 1671603025.498129},
{"id": 70729, "rank": 12, "name": "Pole Position", "scraped_at": 1671603025.498129},
{"id": 70761, "rank": 13, "name": "Broken Sword: The Shadow of the Templars", "scraped_at": 1671603025.498129},
{"id": 70950, "rank": 14, "name": "Full Throttle", "scraped_at": 1671603025.498129},
{"id": 71224, "rank": 15, "name": "Super Metroid", "scraped_at": 1671603025.498129},
{"id": 71692, "rank": 16, "name": "X-COM: Terror from the Deep", "scraped_at": 1671603025.498129},
{"id": 71824, "rank": 17, "name": "Red Dead Redemption", "scraped_at": 1671603025.498129},
{"id": 71844, "rank": 18, "name": "Archon: The Light and the Dark", "scraped_at": 1671603025.498129},
{"id": 72053, "rank": 19, "name": "God of War III", "scraped_at": 1671603025.498129},
{"id": 72077, "rank": 20, "name": "Devil May Cry", "scraped_at": 1671603025.498129},
{"id": 74589, "rank": 21, "name": "Curse of the Azure Bonds", "scraped_at": 1671603025.498129},
{"id": 76001, "rank": 22, "name": "BattleTech: The Crescent Hawk's Inception", "scraped_at": 1671603025.498129},
{"id": 76720, "rank": 23, "name": "God of War: Chains of Olympus", "scraped_at": 1671603025.498129},
{"id": 76801, "rank": 24, "name": "Trog!", "scraped_at": 1671603025.498129},
{"id": 77320, "rank": 25, "name": "Portal 2", "scraped_at": 1671603025.498129},
{"id": 77399, "rank": 26, "name": "Airborne Ranger", "scraped_at": 1671603025.498129},
{"id": 77762, "rank": 27, "name": "Stunt Track Racer", "scraped_at": 1671603025.498129},
{"id": 86467, "rank": 28, "name": "The Great Battles of Hannibal", "scraped_at": 1671603025.498129},
{"id": 91313, "rank": 29, "name": "Ataxx", "scraped_at": 1671603025.498129},
{"id": 112270, "rank": 30, "name": "Pok\u00e9mon Trading Card Game Online", "scraped_at": 1671603025.498129},
{"id": 126256, "rank": 31, "name": "Canopy", "scraped_at": 1671603025.498129},
{"id": 138780, "rank": 32, "name": "The Witcher 3: Wild Hunt", "scraped_at": 1671603025.498129},
{"id": 141306, "rank": 33, "name": "Fear Factor Delerium", "scraped_at": 1671603025.498129},
{"id": 156044, "rank": 34, "name": "Batman: Arkham Knight", "scraped_at": 1671603025.498129},
{"id": 156913, "rank": 35, "name": "DUELYST", "scraped_at": 1671603025.498129},
{"id": 157472, "rank": 36, "name": "Assassin's Creed: Unity", "scraped_at": 1671603025.498129},
{"id": 160763, "rank": 37, "name": "Halo 5: Guardians", "scraped_at": 1671603025.498129},
{"id": 165389, "rank": 38, "name": "Hexcells Infinite", "scraped_at": 1671603025.498129},
{"id": 169418, "rank": 39, "name": "The Binding of Isaac: Rebirth", "scraped_at": 1671603025.498129},
{"id": 177757, "rank": 40, "name": "ARK: Survival Evolved", "scraped_at": 1671603025.498129},
{"id": 178902, "rank": 41, "name": "Fallout 4", "scraped_at": 1671603025.498129},
{"id": 179426, "rank": 42, "name": "Card Crawl", "scraped_at": 1671603025.498129},
{"id": 179510, "rank": 43, "name": "DOOM (2016)", "scraped_at": 1671603025.498129},
{"id": 192498, "rank": 44, "name": "The Legend of Zelda: Breath of the Wild", "scraped_at": 1671603025.498129},
{"id": 201336, "rank": 45, "name": "Atari Flashback Classics: Volume 1", "scraped_at": 1671603025.498129},
{"id": 202169, "rank": 46, "name": "Death Stranding", "scraped_at": 1671603025.498129},
{"id": 205021, "rank": 47, "name": "Quadrilateral Cowboy", "scraped_at": 1671603025.498129},
{"id": 208046, "rank": 48, "name": "Soulblight", "scraped_at": 1671603025.498129},
{"id": 211261, "rank": 49, "name": "Red Dead Redemption II", "scraped_at": 1671603025.498129},
{"id": 218233, "rank": 50, "name": "Splatoon 2", "scraped_at": 1671603025.498129}
]