[
{"id": 247167, "rank": 1, "name": "Artifact", "scraped_at": 1645596625.451248},
{"id": 119150, "rank": 2, "name": "Titan HD", "scraped_at": 1645596625.451248},
{"id": 69334, "rank": 3, "name": "The Legend of Zelda: Ocarina of Time", "scraped_at": 1645596625.451248},
{"id": 70437, "rank": 4, "name": "Pharaoh", "scraped_at": 1645596625.451248},
{"id": 70575, "rank": 5, "name": "Baldur's Gate: Dark Alliance", "scraped_at": 1645596625.451248},
{"id": 78725, "rank": 6, "name": "IL-2 Sturmovik: 1946", "scraped_at": 1645596625.451248},
{"id": 140545, "rank": 7, "name": "Hearthstone: Heroes of Warcraft", "scraped_at": 1645596625.451248},
{"id": 146256, "rank": 8, "name": "Brothers: A Tale of Two Sons", "scraped_at": 1645596625.451248},
{"id": 178902, "rank": 9, "name": "Fallout 4", "scraped_at": 1645596625.451248},
{"id": 291007, "rank": 10, "name": "The Quacks of Quedlinburg", "scraped_at": 1645596625.451248},
{"id": 69354, "rank": 11, "name": "Phoenix Wright: Ace Attorney", "scraped_at": 1645596625.451248},
{"id": 69651, "rank": 12, "name": "Advance Wars 2: Black Hole Rising", "scraped_at": 1645596625.451248},
{"id": 69652, "rank": 13, "name": "Advance Wars: Dual Strike", "scraped_at": 1645596625.451248},
{"id": 69871, "rank": 14, "name": "BloodRayne 2", "scraped_at": 1645596625.451248},
{"id": 70382, "rank": 15, "name": "Final Fantasy Tactics", "scraped_at": 1645596625.451248},
{"id": 70388, "rank": 16, "name": "Mario & Luigi: Bowser's Inside Story", "scraped_at": 1645596625.451248},
{"id": 70443, "rank": 17, "name": "Gran Turismo 4", "scraped_at": 1645596625.451248},
{"id": 70680, "rank": 18, "name": "The Lord of the Rings: The Third Age", "scraped_at": 1645596625.451248},
{"id": 70682, "rank": 19, "name": "The Lord of the Rings: The Fellowship of the Ring", "scraped_at": 1645596625.451248},
{"id": 70761, "rank": 20, "name": "Broken Sword: The Shadow of the Templars", "scraped_at": 1645596625.451248},
{"id": 71257, "rank": 21, "name": "The Legend of Zelda: Spirit Tracks", "scraped_at": 1645596625.451248},
{"id": 72071, "rank": 22, "name": "Ratchet & Clank", "scraped_at": 1645596625.451248},
{"id": 72599, "rank": 23, "name": "Left 4 Dead", "scraped_at": 1645596625.451248},
{"id": 73824, "rank": 24, "name": "XIII", "scraped_at": 1645596625.451248},
{"id": 73881, "rank": 25, "name": "King's Bounty: The Legend", "scraped_at": 1645596625.451248},
{"id": 74411, "rank": 26, "name": "Need for Speed: ProStreet", "scraped_at": 1645596625.451248},
{"id": 74414, "rank": 27, "name": "Need for Speed: Shift", "scraped_at": 1645596625.451248},
{"id": 74563, "rank": 28, "name": "Resident Evil - Code: Veronica", "scraped_at": 1645596625.451248},
{"id": 74964, "rank": 29, "name": "Tony Hawk's Pro Skater 3", "scraped_at": 1645596625.451248},
{"id": 75067, "rank": 30, "name": "Harvest Moon: A Wonderful Life", "scraped_at": 1645596625.451248},
{"id": 75147, "rank": 31, "name": "The Legend of Zelda:  Collector's Edition", "scraped_at": 1645596625.451248},
{"id": 75479, "rank": 32, "name": "Dragon Quest Monsters: Joker", "scraped_at": 1645596625.451248},
{"id": 75756, "rank": 33, "name": "Grand Theft Auto: Vice City", "scraped_at": 1645596625.451248},
{"id": 75866, "rank": 34, "name": "Super Monkey Ball", "scraped_at": 1645596625.451248},
{"id": 77691, "rank": 35, "name": "Star Wars: Episode I: The Phantom Menace", "scraped_at": 1645596625.451248},
{"id": 77927, "rank": 36, "name": "5th Fleet", "scraped_at": 1645596625.451248},
{"id": 78297, "rank": 37, "name": "Max Payne", "scraped_at": 1645596625.451248},
{"id": 80852, "rank": 38, "name": "B-17 Flying Fortress: The Mighty 8th!", "scraped_at": 1645596625.451248},
{"id": 81960, "rank": 39, "name": "Minecraft", "scraped_at": 1645596625.451248},
{"id": 82004, "rank": 40, "name": "Goemon's Great Adventure", "scraped_at": 1645596625.451248},
{"id": 82583, "rank": 41, "name": "Assassin's Creed: Brotherhood", "scraped_at": 1645596625.451248},
{"id": 83264, "rank": 42, "name": "Croke", "scraped_at": 1645596625.451248},
{"id": 84330, "rank": 43, "name": "Enslaved: Odyssey to the West", "scraped_at": 1645596625.451248},
{"id": 84628, "rank": 44, "name": "Fallout: New Vegas", "scraped_at": 1645596625.451248},
{"id": 87950, "rank": 45, "name": "EyeToy: Play", "scraped_at": 1645596625.451248},
{"id": 88101, "rank": 46, "name": "The Witcher 2: Assassins of Kings", "scraped_at": 1645596625.451248},
{"id": 89756, "rank": 47, "name": "Star Wars Battlefront Renegade Squadron", "scraped_at": 1645596625.451248},
{"id": 90215, "rank": 48, "name": "The Elder Scrolls V: Skyrim", "scraped_at": 1645596625.451248},
{"id": 90551, "rank": 49, "name": "Devil Kings", "scraped_at": 1645596625.451248},
{"id": 93031, "rank": 50, "name": "Dark Souls", "scraped_at": 1645596625.451248}
]