[
{"id": 247167, "rank": 1, "name": "Artifact", "scraped_at": 1659679840.541928},
{"id": 311869, "rank": 2, "name": "Stray (2022)", "scraped_at": 1659679840.541928},
{"id": 73903, "rank": 3, "name": "Riven: The Sequel to Myst", "scraped_at": 1659679840.541928},
{"id": 81960, "rank": 4, "name": "Minecraft", "scraped_at": 1659679840.541928},
{"id": 140545, "rank": 5, "name": "Hearthstone: Heroes of Warcraft", "scraped_at": 1659679840.541928},
{"id": 194926, "rank": 6, "name": "Stardew Valley", "scraped_at": 1659679840.541928},
{"id": 365390, "rank": 7, "name": "Necesse", "scraped_at": 1659679840.541928},
{"id": 368095, "rank": 8, "name": "POLE", "scraped_at": 1659679840.541928},
{"id": 68414, "rank": 9, "name": "BioShock 2", "scraped_at": 1659679840.541928},
{"id": 68568, "rank": 10, "name": "Super Mario Bros. 3", "scraped_at": 1659679840.541928},
{"id": 69010, "rank": 11, "name": "Panzer Dragoon (1995)", "scraped_at": 1659679840.541928},
{"id": 69163, "rank": 12, "name": "Desert Strike: Return to the Gulf", "scraped_at": 1659679840.541928},
{"id": 70414, "rank": 13, "name": "Planescape: Torment", "scraped_at": 1659679840.541928},
{"id": 70948, "rank": 14, "name": "Maniac Mansion: Day of the Tentacle", "scraped_at": 1659679840.541928},
{"id": 71162, "rank": 15, "name": "Ultima I: The First Age of Darkness", "scraped_at": 1659679840.541928},
{"id": 71546, "rank": 16, "name": "Champions of Krynn", "scraped_at": 1659679840.541928},
{"id": 72013, "rank": 17, "name": "Beneath a Steel Sky", "scraped_at": 1659679840.541928},
{"id": 72586, "rank": 18, "name": "BioShock", "scraped_at": 1659679840.541928},
{"id": 75220, "rank": 19, "name": "Neverwinter Nights (2002)", "scraped_at": 1659679840.541928},
{"id": 77237, "rank": 20, "name": "Advanced Civilization", "scraped_at": 1659679840.541928},
{"id": 77930, "rank": 21, "name": "BattleForge", "scraped_at": 1659679840.541928},
{"id": 78028, "rank": 22, "name": "Birthright: The Gorgon's Alliance", "scraped_at": 1659679840.541928},
{"id": 80050, "rank": 23, "name": "Catan: The Seafarers", "scraped_at": 1659679840.541928},
{"id": 82097, "rank": 24, "name": "Battleship (1993)", "scraped_at": 1659679840.541928},
{"id": 84431, "rank": 25, "name": "Catan: The First Island", "scraped_at": 1659679840.541928},
{"id": 91313, "rank": 26, "name": "Ataxx", "scraped_at": 1659679840.541928},
{"id": 93031, "rank": 27, "name": "Dark Souls", "scraped_at": 1659679840.541928},
{"id": 97962, "rank": 28, "name": "Outside the Scope of VGG", "scraped_at": 1659679840.541928},
{"id": 98484, "rank": 29, "name": "Invasion of the Mutant Space Bats of Doom", "scraped_at": 1659679840.541928},
{"id": 104079, "rank": 30, "name": "Puerto Rico HD", "scraped_at": 1659679840.541928},
{"id": 112270, "rank": 31, "name": "Pok\u00e9mon Trading Card Game Online", "scraped_at": 1659679840.541928},
{"id": 125995, "rank": 32, "name": "Twilight Struggle", "scraped_at": 1659679840.541928},
{"id": 126729, "rank": 33, "name": "Le Havre", "scraped_at": 1659679840.541928},
{"id": 129760, "rank": 34, "name": "San Juan", "scraped_at": 1659679840.541928},
{"id": 131988, "rank": 35, "name": "Can't Stop", "scraped_at": 1659679840.541928},
{"id": 135310, "rank": 36, "name": "Dominant Species", "scraped_at": 1659679840.541928},
{"id": 138156, "rank": 37, "name": "Kerbal Space Program", "scraped_at": 1659679840.541928},
{"id": 138780, "rank": 38, "name": "The Witcher 3: Wild Hunt", "scraped_at": 1659679840.541928},
{"id": 144037, "rank": 39, "name": "Agricola", "scraped_at": 1659679840.541928},
{"id": 148659, "rank": 40, "name": "Pandemic: The Board Game", "scraped_at": 1659679840.541928},
{"id": 156044, "rank": 41, "name": "Batman: Arkham Knight", "scraped_at": 1659679840.541928},
{"id": 172566, "rank": 42, "name": "Homeworld Remastered Collection", "scraped_at": 1659679840.541928},
{"id": 182943, "rank": 43, "name": "Stellaris", "scraped_at": 1659679840.541928},
{"id": 191150, "rank": 44, "name": "Subnautica", "scraped_at": 1659679840.541928},
{"id": 192498, "rank": 45, "name": "The Legend of Zelda: Breath of the Wild", "scraped_at": 1659679840.541928},
{"id": 202812, "rank": 46, "name": "Agricola: All Creatures Big and Small", "scraped_at": 1659679840.541928},
{"id": 208043, "rank": 47, "name": "Shadow Tactics: Blades of the Shogun", "scraped_at": 1659679840.541928},
{"id": 221278, "rank": 48, "name": "Hollow Knight", "scraped_at": 1659679840.541928},
{"id": 223693, "rank": 49, "name": "Constantinople", "scraped_at": 1659679840.541928},
{"id": 230554, "rank": 50, "name": "Friday", "scraped_at": 1659679840.541928}
]