[
{"id": 261209, "rank": 1, "name": "Gloomhaven", "scraped_at": 1652940640.347256},
{"id": 77320, "rank": 2, "name": "Portal 2", "scraped_at": 1652940640.347256},
{"id": 326714, "rank": 3, "name": "If Found...", "scraped_at": 1652940640.347256},
{"id": 143975, "rank": 4, "name": "Super Mario 3D World", "scraped_at": 1652940640.347256},
{"id": 156913, "rank": 5, "name": "DUELYST", "scraped_at": 1652940640.347256},
{"id": 230070, "rank": 6, "name": "Legendary DXP: A Fantasy Deck Building Game", "scraped_at": 1652940640.347256},
{"id": 230554, "rank": 7, "name": "Friday", "scraped_at": 1652940640.347256},
{"id": 234379, "rank": 8, "name": "Through the Ages", "scraped_at": 1652940640.347256},
{"id": 312163, "rank": 9, "name": "Popup Dungeon", "scraped_at": 1652940640.347256},
{"id": 318741, "rank": 10, "name": "Super Mario 3D All-Stars", "scraped_at": 1652940640.347256},
{"id": 339166, "rank": 11, "name": "Railroad Ink Challenge", "scraped_at": 1652940640.347256},
{"id": 68407, "rank": 12, "name": "Super Mario Bros.", "scraped_at": 1652940640.347256},
{"id": 68409, "rank": 13, "name": "Super Mario Bros. 2", "scraped_at": 1652940640.347256},
{"id": 68427, "rank": 14, "name": "Portal (2007)", "scraped_at": 1652940640.347256},
{"id": 68430, "rank": 15, "name": "Fallout 3", "scraped_at": 1652940640.347256},
{"id": 68568, "rank": 16, "name": "Super Mario Bros. 3", "scraped_at": 1652940640.347256},
{"id": 68627, "rank": 17, "name": "Star Wars: Knights of the Old Republic", "scraped_at": 1652940640.347256},
{"id": 68628, "rank": 18, "name": "Star Wars: Knights of the Old Republic II \u2013 The Sith Lords", "scraped_at": 1652940640.347256},
{"id": 68691, "rank": 19, "name": "Super Mario Sunshine", "scraped_at": 1652940640.347256},
{"id": 68715, "rank": 20, "name": "Super Mario RPG: Legend of the Seven Stars", "scraped_at": 1652940640.347256},
{"id": 69005, "rank": 21, "name": "Super Smash Bros.", "scraped_at": 1652940640.347256},
{"id": 69009, "rank": 22, "name": "Super Mario 64", "scraped_at": 1652940640.347256},
{"id": 69665, "rank": 23, "name": "Street Fighter II", "scraped_at": 1652940640.347256},
{"id": 70131, "rank": 24, "name": "Super Mario Kart", "scraped_at": 1652940640.347256},
{"id": 70391, "rank": 25, "name": "Super Mario Galaxy", "scraped_at": 1652940640.347256},
{"id": 70722, "rank": 26, "name": "StarCraft", "scraped_at": 1652940640.347256},
{"id": 70790, "rank": 27, "name": "Katamari Damacy", "scraped_at": 1652940640.347256},
{"id": 71028, "rank": 28, "name": "Diablo", "scraped_at": 1652940640.347256},
{"id": 71030, "rank": 29, "name": "Diablo II", "scraped_at": 1652940640.347256},
{"id": 71109, "rank": 30, "name": "Xenogears", "scraped_at": 1652940640.347256},
{"id": 71224, "rank": 31, "name": "Super Metroid", "scraped_at": 1652940640.347256},
{"id": 71598, "rank": 32, "name": "Super Punch-Out!!", "scraped_at": 1652940640.347256},
{"id": 71646, "rank": 33, "name": "Stunt Race FX", "scraped_at": 1652940640.347256},
{"id": 71686, "rank": 34, "name": "Super Mario Galaxy 2", "scraped_at": 1652940640.347256},
{"id": 72379, "rank": 35, "name": "Super Contra", "scraped_at": 1652940640.347256},
{"id": 73131, "rank": 36, "name": "Sid Meier's Civilization Revolution", "scraped_at": 1652940640.347256},
{"id": 73458, "rank": 37, "name": "Super Mario Land", "scraped_at": 1652940640.347256},
{"id": 74049, "rank": 38, "name": "Star Wars: Battlefront (2004)", "scraped_at": 1652940640.347256},
{"id": 74124, "rank": 39, "name": "Red Faction", "scraped_at": 1652940640.347256},
{"id": 74369, "rank": 40, "name": "Stuntman: Ignition", "scraped_at": 1652940640.347256},
{"id": 74669, "rank": 41, "name": "Star Wars: Battlefront II (2005)", "scraped_at": 1652940640.347256},
{"id": 74721, "rank": 42, "name": "HeroQuest: Return of the Witch Lord", "scraped_at": 1652940640.347256},
{"id": 75041, "rank": 43, "name": "Super Castlevania IV", "scraped_at": 1652940640.347256},
{"id": 75065, "rank": 44, "name": "Super Smash Bros. Melee", "scraped_at": 1652940640.347256},
{"id": 75401, "rank": 45, "name": "Super Mario Land 2: 6 Golden Coins", "scraped_at": 1652940640.347256},
{"id": 75402, "rank": 46, "name": "Wario Land: Super Mario Land 3", "scraped_at": 1652940640.347256},
{"id": 75866, "rank": 47, "name": "Super Monkey Ball", "scraped_at": 1652940640.347256},
{"id": 77691, "rank": 48, "name": "Star Wars: Episode I: The Phantom Menace", "scraped_at": 1652940640.347256},
{"id": 78034, "rank": 49, "name": "Star Wars: Rebel Assault", "scraped_at": 1652940640.347256},
{"id": 78057, "rank": 50, "name": "Super Monkey Ball Banana Blitz", "scraped_at": 1652940640.347256}
]