[
{"id": 374324, "rank": 1, "name": "Shadow Tactics: Aiko's Choice", "scraped_at": 1673158212.876438},
{"id": 247167, "rank": 2, "name": "Artifact", "scraped_at": 1673158212.876438},
{"id": 307887, "rank": 3, "name": "First Class Trouble", "scraped_at": 1673158212.876438},
{"id": 323254, "rank": 4, "name": "Tribes of Midgard", "scraped_at": 1673158212.876438},
{"id": 138156, "rank": 5, "name": "Kerbal Space Program", "scraped_at": 1673158212.876438},
{"id": 345575, "rank": 6, "name": "The Serpent Rouge", "scraped_at": 1673158212.876438},
{"id": 74562, "rank": 7, "name": "The Witcher", "scraped_at": 1673158212.876438},
{"id": 76219, "rank": 8, "name": "Syndicate Wars", "scraped_at": 1673158212.876438},
{"id": 88101, "rank": 9, "name": "The Witcher 2: Assassins of Kings", "scraped_at": 1673158212.876438},
{"id": 102942, "rank": 10, "name": "Tales of Xillia", "scraped_at": 1673158212.876438},
{"id": 138780, "rank": 11, "name": "The Witcher 3: Wild Hunt", "scraped_at": 1673158212.876438},
{"id": 156913, "rank": 12, "name": "DUELYST", "scraped_at": 1673158212.876438},
{"id": 172077, "rank": 13, "name": "Tabletop Simulator", "scraped_at": 1673158212.876438},
{"id": 178876, "rank": 14, "name": "Sword Coast Legends", "scraped_at": 1673158212.876438},
{"id": 207782, "rank": 15, "name": "The Witcher 3: Wild Hunt \u2013 Complete Edition", "scraped_at": 1673158212.876438},
{"id": 298464, "rank": 16, "name": "Encased: A Sci-Fi Post-Apocalyptic RPG", "scraped_at": 1673158212.876438},
{"id": 68446, "rank": 17, "name": "The Elder Scrolls IV: Oblivion", "scraped_at": 1673158212.876438},
{"id": 68524, "rank": 18, "name": "Secret of Mana (1993)", "scraped_at": 1673158212.876438},
{"id": 69455, "rank": 19, "name": "We \u2665 Katamari", "scraped_at": 1673158212.876438},
{"id": 70546, "rank": 20, "name": "System Shock 2", "scraped_at": 1673158212.876438},
{"id": 70561, "rank": 21, "name": "Europa Universalis II", "scraped_at": 1673158212.876438},
{"id": 70945, "rank": 22, "name": "The Secret of Monkey Island", "scraped_at": 1673158212.876438},
{"id": 71178, "rank": 23, "name": "Relentless: Twinsen's Adventure", "scraped_at": 1673158212.876438},
{"id": 71795, "rank": 24, "name": "Ratchet & Clank Future: Quest for Booty", "scraped_at": 1673158212.876438},
{"id": 71797, "rank": 25, "name": "Ratchet & Clank Future: A Crack In Time", "scraped_at": 1673158212.876438},
{"id": 72500, "rank": 26, "name": "Final Fantasy Adventure", "scraped_at": 1673158212.876438},
{"id": 72624, "rank": 27, "name": "Command  & Conquer: Generals", "scraped_at": 1673158212.876438},
{"id": 73497, "rank": 28, "name": "Blood Bowl", "scraped_at": 1673158212.876438},
{"id": 73521, "rank": 29, "name": "Grand Theft Auto IV", "scraped_at": 1673158212.876438},
{"id": 73824, "rank": 30, "name": "XIII", "scraped_at": 1673158212.876438},
{"id": 73923, "rank": 31, "name": "Tales of Symphonia", "scraped_at": 1673158212.876438},
{"id": 73954, "rank": 32, "name": "Unreal Tournament 2003", "scraped_at": 1673158212.876438},
{"id": 74270, "rank": 33, "name": "Flight of the Amazon Queen", "scraped_at": 1673158212.876438},
{"id": 74954, "rank": 34, "name": "Worms Forts: Under Siege", "scraped_at": 1673158212.876438},
{"id": 75624, "rank": 35, "name": "Leather Goddesses of Phobos", "scraped_at": 1673158212.876438},
{"id": 75927, "rank": 36, "name": "Prisoner of Ice", "scraped_at": 1673158212.876438},
{"id": 76311, "rank": 37, "name": "Railroad Tycoon 3", "scraped_at": 1673158212.876438},
{"id": 76314, "rank": 38, "name": "OpenTTD", "scraped_at": 1673158212.876438},
{"id": 76744, "rank": 39, "name": "Xevious", "scraped_at": 1673158212.876438},
{"id": 76812, "rank": 40, "name": "Oni", "scraped_at": 1673158212.876438},
{"id": 77820, "rank": 41, "name": "Mount & Blade", "scraped_at": 1673158212.876438},
{"id": 77865, "rank": 42, "name": "Europa Universalis", "scraped_at": 1673158212.876438},
{"id": 78260, "rank": 43, "name": "Clue", "scraped_at": 1673158212.876438},
{"id": 78827, "rank": 44, "name": "Bio Menace", "scraped_at": 1673158212.876438},
{"id": 78901, "rank": 45, "name": "Karnov", "scraped_at": 1673158212.876438},
{"id": 78964, "rank": 46, "name": "Call of Cthulhu: Shadow of the Comet", "scraped_at": 1673158212.876438},
{"id": 79218, "rank": 47, "name": "LEGO Universe", "scraped_at": 1673158212.876438},
{"id": 83005, "rank": 48, "name": "Akalabeth: World of Doom", "scraped_at": 1673158212.876438},
{"id": 85503, "rank": 49, "name": "The Eye of Judgment: Legends", "scraped_at": 1673158212.876438},
{"id": 88684, "rank": 50, "name": "Constructor", "scraped_at": 1673158212.876438}
]