[
{"id": 254538, "rank": 1, "name": "Terraforming Mars", "scraped_at": 1678860635.386047},
{"id": 134943, "rank": 2, "name": "Baldur's Gate: Enhanced Edition", "scraped_at": 1678860635.386047},
{"id": 192498, "rank": 3, "name": "The Legend of Zelda: Breath of the Wild", "scraped_at": 1678860635.386047},
{"id": 227359, "rank": 4, "name": "Dead Cells", "scraped_at": 1678860635.386047},
{"id": 271575, "rank": 5, "name": "Tunche", "scraped_at": 1678860635.386047},
{"id": 312035, "rank": 6, "name": "Space Crew", "scraped_at": 1678860635.386047},
{"id": 340627, "rank": 7, "name": "Guardians of the Galaxy", "scraped_at": 1678860635.386047},
{"id": 72758, "rank": 8, "name": "Heroes of Might and Magic II: The Succession Wars", "scraped_at": 1678860635.386047},
{"id": 84899, "rank": 9, "name": "The Blackwell Legacy", "scraped_at": 1678860635.386047},
{"id": 90215, "rank": 10, "name": "The Elder Scrolls V: Skyrim", "scraped_at": 1678860635.386047},
{"id": 156913, "rank": 11, "name": "DUELYST", "scraped_at": 1678860635.386047},
{"id": 167164, "rank": 12, "name": "Blockstorm", "scraped_at": 1678860635.386047},
{"id": 227111, "rank": 13, "name": "Race for the Galaxy", "scraped_at": 1678860635.386047},
{"id": 229279, "rank": 14, "name": "Ori and the Will of the Wisps", "scraped_at": 1678860635.386047},
{"id": 242971, "rank": 15, "name": "Rise of Industry", "scraped_at": 1678860635.386047},
{"id": 247167, "rank": 16, "name": "Artifact", "scraped_at": 1678860635.386047},
{"id": 257578, "rank": 17, "name": "Ganz Sch\u00f6n Clever", "scraped_at": 1678860635.386047},
{"id": 274071, "rank": 18, "name": "Pok\u00e9mon Sword and Pok\u00e9mon Shield", "scraped_at": 1678860635.386047},
{"id": 297337, "rank": 19, "name": "Warhammer 40,000: Gladius \u2013 Relics of War", "scraped_at": 1678860635.386047},
{"id": 318575, "rank": 20, "name": "Ariel_Knight's Never Yield", "scraped_at": 1678860635.386047},
{"id": 360123, "rank": 21, "name": "Space Warlord Organ Trading Simulator", "scraped_at": 1678860635.386047},
{"id": 68287, "rank": 22, "name": "Master of Orion", "scraped_at": 1678860635.386047},
{"id": 68446, "rank": 23, "name": "The Elder Scrolls IV: Oblivion", "scraped_at": 1678860635.386047},
{"id": 68682, "rank": 24, "name": "Heavy Rain", "scraped_at": 1678860635.386047},
{"id": 69057, "rank": 25, "name": "Castlevania: Symphony of the Night", "scraped_at": 1678860635.386047},
{"id": 69189, "rank": 26, "name": "Civilization II", "scraped_at": 1678860635.386047},
{"id": 69325, "rank": 27, "name": "X-COM: UFO Defense", "scraped_at": 1678860635.386047},
{"id": 69334, "rank": 28, "name": "The Legend of Zelda: Ocarina of Time", "scraped_at": 1678860635.386047},
{"id": 69403, "rank": 29, "name": "Castle Crashers", "scraped_at": 1678860635.386047},
{"id": 69977, "rank": 30, "name": "Civilization III", "scraped_at": 1678860635.386047},
{"id": 70414, "rank": 31, "name": "Planescape: Torment", "scraped_at": 1678860635.386047},
{"id": 70453, "rank": 32, "name": "Master of Orion II: Battle at Antares", "scraped_at": 1678860635.386047},
{"id": 70550, "rank": 33, "name": "Baldur's Gate", "scraped_at": 1678860635.386047},
{"id": 70552, "rank": 34, "name": "Baldur's Gate II: Shadows of Amn", "scraped_at": 1678860635.386047},
{"id": 70688, "rank": 35, "name": "The Movies", "scraped_at": 1678860635.386047},
{"id": 70846, "rank": 36, "name": "Zak McKracken and the Alien Mindbenders", "scraped_at": 1678860635.386047},
{"id": 71028, "rank": 37, "name": "Diablo", "scraped_at": 1678860635.386047},
{"id": 71182, "rank": 38, "name": "Prince of Persia (1989)", "scraped_at": 1678860635.386047},
{"id": 71269, "rank": 39, "name": "Fallout (1997)", "scraped_at": 1678860635.386047},
{"id": 71270, "rank": 40, "name": "Fallout 2", "scraped_at": 1678860635.386047},
{"id": 71692, "rank": 41, "name": "X-COM: Terror from the Deep", "scraped_at": 1678860635.386047},
{"id": 71824, "rank": 42, "name": "Red Dead Redemption", "scraped_at": 1678860635.386047},
{"id": 72435, "rank": 43, "name": "Heroes of Might and Magic: A Strategic Quest", "scraped_at": 1678860635.386047},
{"id": 72759, "rank": 44, "name": "Heroes of Might and Magic II: The Price of Loyalty", "scraped_at": 1678860635.386047},
{"id": 72762, "rank": 45, "name": "Heroes of Might and Magic III: The Restoration of Erathia", "scraped_at": 1678860635.386047},
{"id": 72885, "rank": 46, "name": "The Elder Scrolls: Chapter II Daggerfall", "scraped_at": 1678860635.386047},
{"id": 73701, "rank": 47, "name": "Spelunky", "scraped_at": 1678860635.386047},
{"id": 73964, "rank": 48, "name": "Alien Assault", "scraped_at": 1678860635.386047},
{"id": 74139, "rank": 49, "name": "Zangband", "scraped_at": 1678860635.386047},
{"id": 74154, "rank": 50, "name": "The Battle for Wesnoth", "scraped_at": 1678860635.386047}
]