[
{"id": 228384, "rank": 1, "name": "Deep Sky Derelicts", "scraped_at": 1680415805.095385},
{"id": 139961, "rank": 2, "name": "The Silent Age", "scraped_at": 1680415805.095385},
{"id": 271575, "rank": 3, "name": "Tunche", "scraped_at": 1680415805.095385},
{"id": 76121, "rank": 4, "name": "Fantasy General", "scraped_at": 1680415805.095385},
{"id": 77808, "rank": 5, "name": "Star Wars: Rebellion", "scraped_at": 1680415805.095385},
{"id": 79532, "rank": 6, "name": "Metal Slug", "scraped_at": 1680415805.095385},
{"id": 144695, "rank": 7, "name": "Dying Light", "scraped_at": 1680415805.095385},
{"id": 250911, "rank": 8, "name": "Meteorfall: Journeys", "scraped_at": 1680415805.095385},
{"id": 252292, "rank": 9, "name": "Alwa's Awakening", "scraped_at": 1680415805.095385},
{"id": 68409, "rank": 10, "name": "Super Mario Bros. 2", "scraped_at": 1680415805.095385},
{"id": 68430, "rank": 11, "name": "Fallout 3", "scraped_at": 1680415805.095385},
{"id": 68569, "rank": 12, "name": "Super Mario World", "scraped_at": 1680415805.095385},
{"id": 68978, "rank": 13, "name": "Tales of Phantasia", "scraped_at": 1680415805.095385},
{"id": 69177, "rank": 14, "name": "Street Fighter Alpha 3", "scraped_at": 1680415805.095385},
{"id": 69708, "rank": 15, "name": "Beyond Good & Evil", "scraped_at": 1680415805.095385},
{"id": 70193, "rank": 16, "name": "Mario Tennis (N64)", "scraped_at": 1680415805.095385},
{"id": 70561, "rank": 17, "name": "Europa Universalis II", "scraped_at": 1680415805.095385},
{"id": 70743, "rank": 18, "name": "Quest for Glory II: Trial by Fire", "scraped_at": 1680415805.095385},
{"id": 71076, "rank": 19, "name": "Star Wars: Dark Forces", "scraped_at": 1680415805.095385},
{"id": 71171, "rank": 20, "name": "Crusader: No Remorse", "scraped_at": 1680415805.095385},
{"id": 71620, "rank": 21, "name": "DuckTales", "scraped_at": 1680415805.095385},
{"id": 71706, "rank": 22, "name": "Donkey Kong Country 3: Dixie Kong's Double Trouble", "scraped_at": 1680415805.095385},
{"id": 71901, "rank": 23, "name": "Bubble Bobble", "scraped_at": 1680415805.095385},
{"id": 72053, "rank": 24, "name": "God of War III", "scraped_at": 1680415805.095385},
{"id": 72069, "rank": 25, "name": "The Legend of Zelda: Twilight Princess", "scraped_at": 1680415805.095385},
{"id": 72379, "rank": 26, "name": "Super Contra", "scraped_at": 1680415805.095385},
{"id": 72503, "rank": 27, "name": "Castlevania (1986)", "scraped_at": 1680415805.095385},
{"id": 72510, "rank": 28, "name": "The Elder Scrolls III: Bloodmoon", "scraped_at": 1680415805.095385},
{"id": 72849, "rank": 29, "name": "Wolfenstein 3D", "scraped_at": 1680415805.095385},
{"id": 72951, "rank": 30, "name": "Return to Castle Wolfenstein", "scraped_at": 1680415805.095385},
{"id": 73988, "rank": 31, "name": "Rome: Total War", "scraped_at": 1680415805.095385},
{"id": 74163, "rank": 32, "name": "Titan Quest: Immortal Throne", "scraped_at": 1680415805.095385},
{"id": 74334, "rank": 33, "name": "Call of Duty: United Offensive", "scraped_at": 1680415805.095385},
{"id": 74406, "rank": 34, "name": "Need for Speed: Most Wanted", "scraped_at": 1680415805.095385},
{"id": 75498, "rank": 35, "name": "Command & Conquer", "scraped_at": 1680415805.095385},
{"id": 75629, "rank": 36, "name": "Lords of the Realm II", "scraped_at": 1680415805.095385},
{"id": 75748, "rank": 37, "name": "Tony Hawk's Pro Skater", "scraped_at": 1680415805.095385},
{"id": 75923, "rank": 38, "name": "SimCity 3000", "scraped_at": 1680415805.095385},
{"id": 76459, "rank": 39, "name": "Centipede (1980)", "scraped_at": 1680415805.095385},
{"id": 76892, "rank": 40, "name": "Neverwinter Nights 2", "scraped_at": 1680415805.095385},
{"id": 77242, "rank": 41, "name": "Etrian Odyssey II: Heroes of Lagaard", "scraped_at": 1680415805.095385},
{"id": 77320, "rank": 42, "name": "Portal 2", "scraped_at": 1680415805.095385},
{"id": 77524, "rank": 43, "name": "Colin McRae Rally", "scraped_at": 1680415805.095385},
{"id": 77717, "rank": 44, "name": "Archimedean Dynasty", "scraped_at": 1680415805.095385},
{"id": 78037, "rank": 45, "name": "Age of Wonders", "scraped_at": 1680415805.095385},
{"id": 78460, "rank": 46, "name": "Majesty: The Fantasy Kingdom Sim", "scraped_at": 1680415805.095385},
{"id": 78651, "rank": 47, "name": "Colin McRae Rally 2.0", "scraped_at": 1680415805.095385},
{"id": 79126, "rank": 48, "name": "Legacy of Kain: Soul Reaver", "scraped_at": 1680415805.095385},
{"id": 79582, "rank": 49, "name": "Phantasy Star IV", "scraped_at": 1680415805.095385},
{"id": 79676, "rank": 50, "name": "Sid Meier's Pirates! Gold", "scraped_at": 1680415805.095385}
]