[
{"id": 352803, "rank": 1, "name": "Everdell", "scraped_at": 1685686220.296632},
{"id": 364504, "rank": 2, "name": "Hero Realms", "scraped_at": 1685686220.296632},
{"id": 242969, "rank": 3, "name": "Into the Breach", "scraped_at": 1685686220.296632},
{"id": 374944, "rank": 4, "name": "Roll Player", "scraped_at": 1685686220.296632},
{"id": 177350, "rank": 5, "name": "Environmental Station Alpha", "scraped_at": 1685686220.296632},
{"id": 282340, "rank": 6, "name": "The Legend of Zelda: Tears of the Kingdom", "scraped_at": 1685686220.296632},
{"id": 289137, "rank": 7, "name": "Romance of the Three Kingdoms XIV", "scraped_at": 1685686220.296632},
{"id": 68397, "rank": 8, "name": "Mass Effect 2", "scraped_at": 1685686220.296632},
{"id": 78919, "rank": 9, "name": "Kingdom Under Fire: Heroes", "scraped_at": 1685686220.296632},
{"id": 125995, "rank": 10, "name": "Twilight Struggle", "scraped_at": 1685686220.296632},
{"id": 140545, "rank": 11, "name": "Hearthstone: Heroes of Warcraft", "scraped_at": 1685686220.296632},
{"id": 247167, "rank": 12, "name": "Artifact", "scraped_at": 1685686220.296632},
{"id": 294774, "rank": 13, "name": "Wildermyth", "scraped_at": 1685686220.296632},
{"id": 311992, "rank": 14, "name": "Fights In Tight Spaces", "scraped_at": 1685686220.296632},
{"id": 319862, "rank": 15, "name": "Hogwarts Legacy", "scraped_at": 1685686220.296632},
{"id": 70387, "rank": 16, "name": "Mario & Luigi: Partners in Time", "scraped_at": 1685686220.296632},
{"id": 70526, "rank": 17, "name": "H\u03bbLF-LIFE: Blue Shift", "scraped_at": 1685686220.296632},
{"id": 73444, "rank": 18, "name": "Kingdom of Loathing", "scraped_at": 1685686220.296632},
{"id": 75152, "rank": 19, "name": "Solium Infernum", "scraped_at": 1685686220.296632},
{"id": 76314, "rank": 20, "name": "OpenTTD", "scraped_at": 1685686220.296632},
{"id": 76410, "rank": 21, "name": "Mega Man", "scraped_at": 1685686220.296632},
{"id": 76533, "rank": 22, "name": "Spacewar!", "scraped_at": 1685686220.296632},
{"id": 78940, "rank": 23, "name": "Legaia 2: Duel Saga", "scraped_at": 1685686220.296632},
{"id": 80597, "rank": 24, "name": "Zelda: The Wand of Gamelon", "scraped_at": 1685686220.296632},
{"id": 81960, "rank": 25, "name": "Minecraft", "scraped_at": 1685686220.296632},
{"id": 82847, "rank": 26, "name": "Demolition Man (Run-and-gun)", "scraped_at": 1685686220.296632},
{"id": 82851, "rank": 27, "name": "Farm Frenzy", "scraped_at": 1685686220.296632},
{"id": 82880, "rank": 28, "name": "Die Hard", "scraped_at": 1685686220.296632},
{"id": 82881, "rank": 29, "name": "Disney's Beauty and the Beast", "scraped_at": 1685686220.296632},
{"id": 82885, "rank": 30, "name": "Disney's Beauty and the Beast: Belle's Quest", "scraped_at": 1685686220.296632},
{"id": 82890, "rank": 31, "name": "Disney's Bonkers", "scraped_at": 1685686220.296632},
{"id": 82946, "rank": 32, "name": "Sweevo's World", "scraped_at": 1685686220.296632},
{"id": 83031, "rank": 33, "name": "Xenocide", "scraped_at": 1685686220.296632},
{"id": 83053, "rank": 34, "name": "Rat Attack", "scraped_at": 1685686220.296632},
{"id": 83058, "rank": 35, "name": "Dragon Fighter", "scraped_at": 1685686220.296632},
{"id": 83070, "rank": 36, "name": "Mighty Morphin Power Rangers: The Movie", "scraped_at": 1685686220.296632},
{"id": 83080, "rank": 37, "name": "Disney's The Jungle Book", "scraped_at": 1685686220.296632},
{"id": 83100, "rank": 38, "name": "Lemony Snicket's A Series of Unfortunate Events", "scraped_at": 1685686220.296632},
{"id": 83113, "rank": 39, "name": "Monsters, Inc. Scare Island", "scraped_at": 1685686220.296632},
{"id": 83179, "rank": 40, "name": "Deception III: Dark Delusion", "scraped_at": 1685686220.296632},
{"id": 83206, "rank": 41, "name": "Warrior Kings", "scraped_at": 1685686220.296632},
{"id": 83260, "rank": 42, "name": "Star Wars: TIE Fighter Collector's CD-ROM", "scraped_at": 1685686220.296632},
{"id": 83308, "rank": 43, "name": "Duck Maze", "scraped_at": 1685686220.296632},
{"id": 83313, "rank": 44, "name": "Eliminator Boat Duel", "scraped_at": 1685686220.296632},
{"id": 83345, "rank": 45, "name": "Hole in One Golf", "scraped_at": 1685686220.296632},
{"id": 83469, "rank": 46, "name": "The Elder Scrolls IV: Oblivion \u2013 Game of the Year Edition", "scraped_at": 1685686220.296632},
{"id": 83478, "rank": 47, "name": "Bagman", "scraped_at": 1685686220.296632},
{"id": 83665, "rank": 48, "name": "Magic Boy", "scraped_at": 1685686220.296632},
{"id": 83666, "rank": 49, "name": "The Mask", "scraped_at": 1685686220.296632},
{"id": 83675, "rank": 50, "name": "Robin of the Wood", "scraped_at": 1685686220.296632}
]