[
{"id": 381489, "rank": 1, "name": "Unmatched: Digital Edition", "scraped_at": 1715667047.032066},
{"id": 400187, "rank": 2, "name": "Discordia", "scraped_at": 1715667047.032066},
{"id": 383048, "rank": 3, "name": "Capital Lux 2", "scraped_at": 1715667047.032066},
{"id": 76975, "rank": 4, "name": "Marathon", "scraped_at": 1715667047.032066},
{"id": 393622, "rank": 5, "name": "Twilight Struggle: Red Sea", "scraped_at": 1715667047.032066},
{"id": 411052, "rank": 6, "name": "Beecarbonize", "scraped_at": 1715667047.032066},
{"id": 380043, "rank": 7, "name": "Fantasy Realms by WizKids", "scraped_at": 1715667047.032066},
{"id": 403425, "rank": 8, "name": "Power Grid Boardgame", "scraped_at": 1715667047.032066},
{"id": 380042, "rank": 9, "name": "Super Mega Lucky Box", "scraped_at": 1715667047.032066},
{"id": 406581, "rank": 10, "name": "Fleet the Dice Game", "scraped_at": 1715667047.032066},
{"id": 389413, "rank": 11, "name": "Numbsters", "scraped_at": 1715667047.032066},
{"id": 388711, "rank": 12, "name": "Munchkin Digital", "scraped_at": 1715667047.032066},
{"id": 417173, "rank": 13, "name": "Dune: Imperium", "scraped_at": 1715667047.032066},
{"id": 71465, "rank": 14, "name": "Alan Wake", "scraped_at": 1715667047.032066},
{"id": 140545, "rank": 15, "name": "Hearthstone: Heroes of Warcraft", "scraped_at": 1715667047.032066},
{"id": 156913, "rank": 16, "name": "DUELYST", "scraped_at": 1715667047.032066},
{"id": 179509, "rank": 17, "name": "Dishonored 2", "scraped_at": 1715667047.032066},
{"id": 247167, "rank": 18, "name": "Artifact", "scraped_at": 1715667047.032066},
{"id": 261226, "rank": 19, "name": "Spirit Island", "scraped_at": 1715667047.032066},
{"id": 282124, "rank": 20, "name": "Elden Ring", "scraped_at": 1715667047.032066},
{"id": 348014, "rank": 21, "name": "Concordia: Digital Edition", "scraped_at": 1715667047.032066},
{"id": 412996, "rank": 22, "name": "Balatro", "scraped_at": 1715667047.032066},
{"id": 413988, "rank": 23, "name": "Stellar Blade", "scraped_at": 1715667047.032066},
{"id": 69083, "rank": 24, "name": "Halo: Reach", "scraped_at": 1715667047.032066},
{"id": 69301, "rank": 25, "name": "Eye of the Beholder II: The Legend of Darkmoon", "scraped_at": 1715667047.032066},
{"id": 69742, "rank": 26, "name": "Indigo Prophecy", "scraped_at": 1715667047.032066},
{"id": 70550, "rank": 27, "name": "Baldur's Gate", "scraped_at": 1715667047.032066},
{"id": 70838, "rank": 28, "name": "The Beast Within: A Gabriel Knight Mystery", "scraped_at": 1715667047.032066},
{"id": 70839, "rank": 29, "name": "Gabriel Knight 3: Blood of the Sacred, Blood of the Damned", "scraped_at": 1715667047.032066},
{"id": 70847, "rank": 30, "name": "Indiana Jones and the Last Crusade: The Graphic Adventure", "scraped_at": 1715667047.032066},
{"id": 70947, "rank": 31, "name": "Indiana Jones and the Fate of Atlantis", "scraped_at": 1715667047.032066},
{"id": 70950, "rank": 32, "name": "Full Throttle", "scraped_at": 1715667047.032066},
{"id": 71269, "rank": 33, "name": "Fallout (1997)", "scraped_at": 1715667047.032066},
{"id": 71270, "rank": 34, "name": "Fallout 2", "scraped_at": 1715667047.032066},
{"id": 71306, "rank": 35, "name": "Grandia II", "scraped_at": 1715667047.032066},
{"id": 72888, "rank": 36, "name": "Fallout Tactics: Brotherhood of Steel", "scraped_at": 1715667047.032066},
{"id": 72940, "rank": 37, "name": "Ancient Domains of Mystery", "scraped_at": 1715667047.032066},
{"id": 74489, "rank": 38, "name": "Indiana Jones and the Infernal Machine", "scraped_at": 1715667047.032066},
{"id": 74654, "rank": 39, "name": "Star Wars: X-Wing", "scraped_at": 1715667047.032066},
{"id": 74881, "rank": 40, "name": "Wasteland", "scraped_at": 1715667047.032066},
{"id": 75048, "rank": 41, "name": "Alpha Protocol", "scraped_at": 1715667047.032066},
{"id": 76125, "rank": 42, "name": "Star General", "scraped_at": 1715667047.032066},
{"id": 76746, "rank": 43, "name": "Kororinpa: Marble Mania", "scraped_at": 1715667047.032066},
{"id": 76767, "rank": 44, "name": "The Last Guardian", "scraped_at": 1715667047.032066},
{"id": 77338, "rank": 45, "name": "Bad Dudes Vs. DragonNinja", "scraped_at": 1715667047.032066},
{"id": 78154, "rank": 46, "name": "Baldur's Gate 4 in 1 Boxset", "scraped_at": 1715667047.032066},
{"id": 78534, "rank": 47, "name": "In Cold Blood", "scraped_at": 1715667047.032066},
{"id": 79897, "rank": 48, "name": "Spelljammer: Pirates of Realmspace", "scraped_at": 1715667047.032066},
{"id": 80197, "rank": 49, "name": "Duke Nukem: Manhattan Project", "scraped_at": 1715667047.032066},
{"id": 81506, "rank": 50, "name": "Pax Imperia", "scraped_at": 1715667047.032066}
]