[
{"id": 362638, "rank": 1, "name": "Slice & Dice", "scraped_at": 1710137421.280278},
{"id": 156913, "rank": 2, "name": "DUELYST", "scraped_at": 1710137421.280278},
{"id": 69334, "rank": 3, "name": "The Legend of Zelda: Ocarina of Time", "scraped_at": 1710137421.280278},
{"id": 68742, "rank": 4, "name": "Perfect Dark (2000)", "scraped_at": 1710137421.280278},
{"id": 73458, "rank": 5, "name": "Super Mario Land", "scraped_at": 1710137421.280278},
{"id": 91313, "rank": 6, "name": "Ataxx", "scraped_at": 1710137421.280278},
{"id": 102345, "rank": 7, "name": "Mass Effect 3", "scraped_at": 1710137421.280278},
{"id": 135781, "rank": 8, "name": "Fortnite Battle Royale", "scraped_at": 1710137421.280278},
{"id": 176168, "rank": 9, "name": "Deus Ex: Mankind Divided", "scraped_at": 1710137421.280278},
{"id": 232757, "rank": 10, "name": "Warbanners", "scraped_at": 1710137421.280278},
{"id": 254909, "rank": 11, "name": "Control (2019)", "scraped_at": 1710137421.280278},
{"id": 68427, "rank": 12, "name": "Portal (2007)", "scraped_at": 1710137421.280278},
{"id": 68429, "rank": 13, "name": "New Super Mario Bros. Wii", "scraped_at": 1710137421.280278},
{"id": 68438, "rank": 14, "name": "Darksiders", "scraped_at": 1710137421.280278},
{"id": 68608, "rank": 15, "name": "SoulCalibur", "scraped_at": 1710137421.280278},
{"id": 68744, "rank": 16, "name": "Paper Mario", "scraped_at": 1710137421.280278},
{"id": 68992, "rank": 17, "name": "Chrono Trigger", "scraped_at": 1710137421.280278},
{"id": 69072, "rank": 18, "name": "Carcassonne (2007)", "scraped_at": 1710137421.280278},
{"id": 69079, "rank": 19, "name": "Trials HD", "scraped_at": 1710137421.280278},
{"id": 69365, "rank": 20, "name": "Hotel Dusk: Room 215", "scraped_at": 1710137421.280278},
{"id": 69403, "rank": 21, "name": "Castle Crashers", "scraped_at": 1710137421.280278},
{"id": 69417, "rank": 22, "name": "The Legend of Zelda: A Link to the Past", "scraped_at": 1710137421.280278},
{"id": 69941, "rank": 23, "name": "Animal Crossing: Wild World", "scraped_at": 1710137421.280278},
{"id": 70039, "rank": 24, "name": "Starflight", "scraped_at": 1710137421.280278},
{"id": 70133, "rank": 25, "name": "Mario Kart 64", "scraped_at": 1710137421.280278},
{"id": 70135, "rank": 26, "name": "Mario Kart Double Dash!!", "scraped_at": 1710137421.280278},
{"id": 70187, "rank": 27, "name": "Super Mario Strikers", "scraped_at": 1710137421.280278},
{"id": 70382, "rank": 28, "name": "Final Fantasy Tactics", "scraped_at": 1710137421.280278},
{"id": 70383, "rank": 29, "name": "Final Fantasy Tactics Advance", "scraped_at": 1710137421.280278},
{"id": 70388, "rank": 30, "name": "Mario & Luigi: Bowser's Inside Story", "scraped_at": 1710137421.280278},
{"id": 70390, "rank": 31, "name": "Super Paper Mario", "scraped_at": 1710137421.280278},
{"id": 70497, "rank": 32, "name": "NetHack", "scraped_at": 1710137421.280278},
{"id": 70557, "rank": 33, "name": "H\u03bbLF-LIFE\u00b2: Episode One", "scraped_at": 1710137421.280278},
{"id": 70683, "rank": 34, "name": "The Lord of the Rings: The Return of the King", "scraped_at": 1710137421.280278},
{"id": 70966, "rank": 35, "name": "Wii Sports Resort", "scraped_at": 1710137421.280278},
{"id": 71144, "rank": 36, "name": "Viewtiful Joe", "scraped_at": 1710137421.280278},
{"id": 71236, "rank": 37, "name": "New Super Mario Bros.", "scraped_at": 1710137421.280278},
{"id": 71544, "rank": 38, "name": "Elite", "scraped_at": 1710137421.280278},
{"id": 71847, "rank": 39, "name": "Caveman Ugh-Lympics", "scraped_at": 1710137421.280278},
{"id": 71974, "rank": 40, "name": "California Games", "scraped_at": 1710137421.280278},
{"id": 72416, "rank": 41, "name": "Master of Magic (1994)", "scraped_at": 1710137421.280278},
{"id": 72529, "rank": 42, "name": "Wonder Boy", "scraped_at": 1710137421.280278},
{"id": 72940, "rank": 43, "name": "Ancient Domains of Mystery", "scraped_at": 1710137421.280278},
{"id": 72953, "rank": 44, "name": "Rogue", "scraped_at": 1710137421.280278},
{"id": 73274, "rank": 45, "name": "Angband", "scraped_at": 1710137421.280278},
{"id": 73471, "rank": 46, "name": "Dragon Age: Origins \u2013 Awakening", "scraped_at": 1710137421.280278},
{"id": 73493, "rank": 47, "name": "Golden Sun: The Lost Age", "scraped_at": 1710137421.280278},
{"id": 73799, "rank": 48, "name": "Sid Meier's Alpha Centauri", "scraped_at": 1710137421.280278},
{"id": 74406, "rank": 49, "name": "Need for Speed: Most Wanted", "scraped_at": 1710137421.280278},
{"id": 74717, "rank": 50, "name": "Dune II: The Building of a Dynasty", "scraped_at": 1710137421.280278}
]